alignment_network.v
module alignment_network(
    InBuf,
    reverse,
    align_start,
    OutBuf
);
    // constants
    parameter DATA_WIDTH = 64;
    parameter WORD_WIDTH = 8;

    input [DATA_WIDTH-1:0] InBuf;
    input reverse;
    input [2:0] align_start;
    //input [clog2(DATA_WIDTH/WORD_WIDTH)-1:0] align_start;
    output [DATA_WIDTH-1:0] OutBuf;

    wire [2:0] sel;

    wire [WORD_WIDTH-1:0] InBuf_data [DATA_WIDTH/WORD_WIDTH-1:0];
    wire [WORD_WIDTH-1:0] OutBuf_data [DATA_WIDTH/WORD_WIDTH-1:0];

    assign sel = reverse ? (DATA_WIDTH/WORD_WIDTH) - align_start : align_start;

    genvar i;
    generate
        for (i = 0; i < DATA_WIDTH/WORD_WIDTH; i = i + 1)
        begin
            assign  InBuf_data[i] = InBuf[((WORD_WIDTH)*(i+1)-1):(WORD_WIDTH)*i];

            mux8to1 #(.DATA_WIDTH(WORD_WIDTH), .SEL_WIDTH(3)) MUX_Data(
                .Out(OutBuf_data[i]),
                //.Out(OutBuf[((DATA_WIDTH/8)*(i+1)-1):(DATA_WIDTH/8)*i]),
                .Sel(sel),
                .In1(InBuf_data[(i)&3'b111]),
                .In2(InBuf_data[(i+1)&3'b111]),
                .In3(InBuf_data[(i+2)&3'b111]),
                .In4(InBuf_data[(i+3)&3'b111]),
                .In5(InBuf_data[(i+4)&3'b111]),
                .In6(InBuf_data[(i+5)&3'b111]),
                .In7(InBuf_data[(i+6)&3'b111]),
                .In8(InBuf_data[(i+7)&3'b111])
                );

            assign OutBuf[((WORD_WIDTH)*(i+1)-1):(WORD_WIDTH)*i] = OutBuf_data[i];
        end
    endgenerate
endmodule


module mux8to1( Out,
      Sel,
      In1,
      In2,
      In3,
      In4,
      In5,
      In6,
      In7,
      In8
);
    parameter DATA_WIDTH = 8;
    parameter SEL_WIDTH = 3;

    input [DATA_WIDTH-1:0]  In1, In2, In3, In4, In5, In6, In7, In8;

    input [SEL_WIDTH-1:0] Sel; //The three bit selection line
    output [DATA_WIDTH-1:0] Out; //The single 8-bit output line of the Mux

    reg [DATA_WIDTH-1:0] Out;

    //Check the state of the input lines

    always @ (In1 or In2 or In3 or In4 or In5 or In6 or In7 or In8 or Sel)
    begin
     case (Sel)
      3'b000 : Out = In1;
      3'b001 : Out = In2;
      3'b010 : Out = In3;
      3'b011 : Out = In4;
      3'b100 : Out = In5;
      3'b101 : Out = In6;
      3'b110 : Out = In7;
      3'b111 : Out = In8;
      default : Out = 8'bx;
      //If input is undefined then output is undefined
     endcase
    end
endmodule

module DeMux1to8(in,
                sel,
                out
);
input in;
input [2:0] sel;
output reg [7:0] out =0;

    always @ (in or sel)
    begin
     case (sel)
      3'b000 : out = in;
      3'b001 : out = in << 1;
      3'b010 : out = in << 2;
      3'b011 : out = in << 3;
      3'b100 : out = in << 4;
      3'b101 : out = in << 5;
      3'b110 : out = in << 6;
      3'b111 : out = in << 7;
      default : out = 8'bx;
      //If input is undefined then output is undefined
     endcase
    end
endmodule



// module alignment_net_tb();
//     parameter DATA_WIDTH = 64;
//
//     reg [DATA_WIDTH-1:0] InBuf;
//     reg reverse;
//     reg [2:0] align_start;
//     wire [DATA_WIDTH-1:0] OutBuf;
//
//
//     alignment_network dut(
//         InBuf,
//         reverse,
//         align_start,
//         OutBuf
//     );
//
//     always #5 align_start = align_start + 1;
//     initial begin
//         $dumpfile("alignment_net_tb.vcd");
//         $dumpvars(0,alignment_net_tb);
//         reverse = 0;
//         InBuf = 64'h0123456789ABCDEF;
//         align_start = 8'h01;
//         #5 align_start = 0;
//         #60 reverse = 1;
//         #60 $finish;
//     end
//
// endmodule

alignment_net_tb.v
module alignment_net_tb();
    parameter DATA_WIDTH = 64;

    reg [DATA_WIDTH-1:0] InBuf;
    reg reverse;
    reg [2:0] align_start;
    wire [DATA_WIDTH-1:0] OutBuf;


    alignment_network dut(
        InBuf,
        reverse,
        align_start,
        OutBuf
    );

    always #5 align_start = align_start + 1;
    initial begin
        $dumpfile("alignment_net_tb.vcd");
        $dumpvars(0,alignment_net_tb);
        reverse = 0;
        InBuf = 64'h0123456789ABCDEF;
        align_start = 8'h01;
        #5 align_start = 0;
        #60 reverse = 1;
        #60 $finish;
    end

endmodule

alignment_net_tb.vcd
$date
	Wed Jan 17 17:57:59 2018
$end
$version
	Icarus Verilog
$end
$timescale
	1s
$end
$scope module alignment_net_tb $end
$var wire 64 ! OutBuf [63:0] $end
$var reg 64 " InBuf [63:0] $end
$var reg 3 # align_start [2:0] $end
$var reg 1 $ reverse $end
$scope module dut $end
$var wire 64 % InBuf [63:0] $end
$var wire 3 & align_start [2:0] $end
$var wire 1 $ reverse $end
$var wire 3 ' sel [2:0] $end
$var wire 64 ( OutBuf [63:0] $end
$scope begin genblk1[0] $end
$scope module MUX_Data $end
$var wire 8 ) In1 [7:0] $end
$var wire 8 * In2 [7:0] $end
$var wire 8 + In3 [7:0] $end
$var wire 8 , In4 [7:0] $end
$var wire 8 - In5 [7:0] $end
$var wire 8 . In6 [7:0] $end
$var wire 8 / In7 [7:0] $end
$var wire 8 0 In8 [7:0] $end
$var wire 3 1 Sel [2:0] $end
$var reg 8 2 Out [7:0] $end
$upscope $end
$upscope $end
$scope begin genblk1[1] $end
$scope module MUX_Data $end
$var wire 8 3 In1 [7:0] $end
$var wire 8 4 In2 [7:0] $end
$var wire 8 5 In3 [7:0] $end
$var wire 8 6 In4 [7:0] $end
$var wire 8 7 In5 [7:0] $end
$var wire 8 8 In6 [7:0] $end
$var wire 8 9 In7 [7:0] $end
$var wire 8 : In8 [7:0] $end
$var wire 3 ; Sel [2:0] $end
$var reg 8 < Out [7:0] $end
$upscope $end
$upscope $end
$scope begin genblk1[2] $end
$scope module MUX_Data $end
$var wire 8 = In1 [7:0] $end
$var wire 8 > In2 [7:0] $end
$var wire 8 ? In3 [7:0] $end
$var wire 8 @ In4 [7:0] $end
$var wire 8 A In5 [7:0] $end
$var wire 8 B In6 [7:0] $end
$var wire 8 C In7 [7:0] $end
$var wire 8 D In8 [7:0] $end
$var wire 3 E Sel [2:0] $end
$var reg 8 F Out [7:0] $end
$upscope $end
$upscope $end
$scope begin genblk1[3] $end
$scope module MUX_Data $end
$var wire 8 G In1 [7:0] $end
$var wire 8 H In2 [7:0] $end
$var wire 8 I In3 [7:0] $end
$var wire 8 J In4 [7:0] $end
$var wire 8 K In5 [7:0] $end
$var wire 8 L In6 [7:0] $end
$var wire 8 M In7 [7:0] $end
$var wire 8 N In8 [7:0] $end
$var wire 3 O Sel [2:0] $end
$var reg 8 P Out [7:0] $end
$upscope $end
$upscope $end
$scope begin genblk1[4] $end
$scope module MUX_Data $end
$var wire 8 Q In1 [7:0] $end
$var wire 8 R In2 [7:0] $end
$var wire 8 S In3 [7:0] $end
$var wire 8 T In4 [7:0] $end
$var wire 8 U In5 [7:0] $end
$var wire 8 V In6 [7:0] $end
$var wire 8 W In7 [7:0] $end
$var wire 8 X In8 [7:0] $end
$var wire 3 Y Sel [2:0] $end
$var reg 8 Z Out [7:0] $end
$upscope $end
$upscope $end
$scope begin genblk1[5] $end
$scope module MUX_Data $end
$var wire 8 [ In1 [7:0] $end
$var wire 8 \ In2 [7:0] $end
$var wire 8 ] In3 [7:0] $end
$var wire 8 ^ In4 [7:0] $end
$var wire 8 _ In5 [7:0] $end
$var wire 8 ` In6 [7:0] $end
$var wire 8 a In7 [7:0] $end
$var wire 8 b In8 [7:0] $end
$var wire 3 c Sel [2:0] $end
$var reg 8 d Out [7:0] $end
$upscope $end
$upscope $end
$scope begin genblk1[6] $end
$scope module MUX_Data $end
$var wire 8 e In1 [7:0] $end
$var wire 8 f In2 [7:0] $end
$var wire 8 g In3 [7:0] $end
$var wire 8 h In4 [7:0] $end
$var wire 8 i In5 [7:0] $end
$var wire 8 j In6 [7:0] $end
$var wire 8 k In7 [7:0] $end
$var wire 8 l In8 [7:0] $end
$var wire 3 m Sel [2:0] $end
$var reg 8 n Out [7:0] $end
$upscope $end
$upscope $end
$scope begin genblk1[7] $end
$scope module MUX_Data $end
$var wire 8 o In1 [7:0] $end
$var wire 8 p In2 [7:0] $end
$var wire 8 q In3 [7:0] $end
$var wire 8 r In4 [7:0] $end
$var wire 8 s In5 [7:0] $end
$var wire 8 t In6 [7:0] $end
$var wire 8 u In7 [7:0] $end
$var wire 8 v In8 [7:0] $end
$var wire 3 w Sel [2:0] $end
$var reg 8 x Out [7:0] $end
$upscope $end
$upscope $end
$upscope $end
$upscope $end
$enddefinitions $end
#0
$dumpvars
b11101111 x
b1 w
b100011 v
b1000101 u
b1100111 t
b10001001 s
b10101011 r
b11001101 q
b11101111 p
b1 o
b1 n
b1 m
b1000101 l
b1100111 k
b10001001 j
b10101011 i
b11001101 h
b11101111 g
b1 f
b100011 e
b100011 d
b1 c
b1100111 b
b10001001 a
b10101011 `
b11001101 _
b11101111 ^
b1 ]
b100011 \
b1000101 [
b1000101 Z
b1 Y
b10001001 X
b10101011 W
b11001101 V
b11101111 U
b1 T
b100011 S
b1000101 R
b1100111 Q
b1100111 P
b1 O
b10101011 N
b11001101 M
b11101111 L
b1 K
b100011 J
b1000101 I
b1100111 H
b10001001 G
b10001001 F
b1 E
b11001101 D
b11101111 C
b1 B
b100011 A
b1000101 @
b1100111 ?
b10001001 >
b10101011 =
b10101011 <
b1 ;
b11101111 :
b1 9
b100011 8
b1000101 7
b1100111 6
b10001001 5
b10101011 4
b11001101 3
b11001101 2
b1 1
b1 0
b100011 /
b1000101 .
b1100111 -
b10001001 ,
b10101011 +
b11001101 *
b11101111 )
b1110111100000001001000110100010101100111100010011010101111001101 (
b1 '
b1 &
b100100011010001010110011110001001101010111100110111101111 %
0$
b1 #
b100100011010001010110011110001001101010111100110111101111 "
b1110111100000001001000110100010101100111100010011010101111001101 !
$end
#5
b11101111 2
b11001101 <
b10101011 F
b10001001 P
b1100111 Z
b1000101 d
b100011 n
b100100011010001010110011110001001101010111100110111101111 !
b100100011010001010110011110001001101010111100110111101111 (
b1 x
b0 '
b0 1
b0 ;
b0 E
b0 O
b0 Y
b0 c
b0 m
b0 w
b0 #
b0 &
#10
b11101111 x
b1 n
b100011 d
b1000101 Z
b1100111 P
b10001001 F
b10101011 <
b1110111100000001001000110100010101100111100010011010101111001101 !
b1110111100000001001000110100010101100111100010011010101111001101 (
b11001101 2
b1 '
b1 1
b1 ;
b1 E
b1 O
b1 Y
b1 c
b1 m
b1 w
b1 #
b1 &
#15
b10101011 2
b10001001 <
b1100111 F
b1000101 P
b100011 Z
b1 d
b11101111 n
b1100110111101111000000010010001101000101011001111000100110101011 !
b1100110111101111000000010010001101000101011001111000100110101011 (
b11001101 x
b10 '
b10 1
b10 ;
b10 E
b10 O
b10 Y
b10 c
b10 m
b10 w
b10 #
b10 &
#20
b10101011 x
b11001101 n
b11101111 d
b1 Z
b100011 P
b1000101 F
b1100111 <
b1010101111001101111011110000000100100011010001010110011110001001 !
b1010101111001101111011110000000100100011010001010110011110001001 (
b10001001 2
b11 '
b11 1
b11 ;
b11 E
b11 O
b11 Y
b11 c
b11 m
b11 w
b11 #
b11 &
#25
b1100111 2
b1000101 <
b100011 F
b1 P
b11101111 Z
b11001101 d
b10101011 n
b1000100110101011110011011110111100000001001000110100010101100111 !
b1000100110101011110011011110111100000001001000110100010101100111 (
b10001001 x
b100 '
b100 1
b100 ;
b100 E
b100 O
b100 Y
b100 c
b100 m
b100 w
b100 #
b100 &
#30
b1100111 x
b10001001 n
b10101011 d
b11001101 Z
b11101111 P
b1 F
b100011 <
b110011110001001101010111100110111101111000000010010001101000101 !
b110011110001001101010111100110111101111000000010010001101000101 (
b1000101 2
b101 '
b101 1
b101 ;
b101 E
b101 O
b101 Y
b101 c
b101 m
b101 w
b101 #
b101 &
#35
b100011 2
b1 <
b11101111 F
b11001101 P
b10101011 Z
b10001001 d
b1100111 n
b100010101100111100010011010101111001101111011110000000100100011 !
b100010101100111100010011010101111001101111011110000000100100011 (
b1000101 x
b110 '
b110 1
b110 ;
b110 E
b110 O
b110 Y
b110 c
b110 m
b110 w
b110 #
b110 &
#40
b100011 x
b1000101 n
b1100111 d
b10001001 Z
b10101011 P
b11001101 F
b11101111 <
b10001101000101011001111000100110101011110011011110111100000001 !
b10001101000101011001111000100110101011110011011110111100000001 (
b1 2
b111 '
b111 1
b111 ;
b111 E
b111 O
b111 Y
b111 c
b111 m
b111 w
b111 #
b111 &
#45
b11101111 2
b11001101 <
b10101011 F
b10001001 P
b1100111 Z
b1000101 d
b100011 n
b100100011010001010110011110001001101010111100110111101111 !
b100100011010001010110011110001001101010111100110111101111 (
b1 x
b0 '
b0 1
b0 ;
b0 E
b0 O
b0 Y
b0 c
b0 m
b0 w
b0 #
b0 &
#50
b11101111 x
b1 n
b100011 d
b1000101 Z
b1100111 P
b10001001 F
b10101011 <
b1110111100000001001000110100010101100111100010011010101111001101 !
b1110111100000001001000110100010101100111100010011010101111001101 (
b11001101 2
b1 '
b1 1
b1 ;
b1 E
b1 O
b1 Y
b1 c
b1 m
b1 w
b1 #
b1 &
#55
b10101011 2
b10001001 <
b1100111 F
b1000101 P
b100011 Z
b1 d
b11101111 n
b1100110111101111000000010010001101000101011001111000100110101011 !
b1100110111101111000000010010001101000101011001111000100110101011 (
b11001101 x
b10 '
b10 1
b10 ;
b10 E
b10 O
b10 Y
b10 c
b10 m
b10 w
b10 #
b10 &
#60
b10101011 x
b11001101 n
b11101111 d
b1 Z
b100011 P
b1000101 F
b1100111 <
b1010101111001101111011110000000100100011010001010110011110001001 !
b1010101111001101111011110000000100100011010001010110011110001001 (
b10001001 2
b11 '
b11 1
b11 ;
b11 E
b11 O
b11 Y
b11 c
b11 m
b11 w
b11 #
b11 &
#65
b1100111 2
b1000101 <
b100011 F
b1 P
b11101111 Z
b11001101 d
b10101011 n
b1000100110101011110011011110111100000001001000110100010101100111 !
b1000100110101011110011011110111100000001001000110100010101100111 (
b10001001 x
b100 '
b100 1
b100 ;
b100 E
b100 O
b100 Y
b100 c
b100 m
b100 w
b100 #
b100 &
1$
#70
b10101011 x
b11001101 n
b11101111 d
b1 Z
b100011 P
b1000101 F
b1100111 <
b1010101111001101111011110000000100100011010001010110011110001001 !
b1010101111001101111011110000000100100011010001010110011110001001 (
b10001001 2
b11 '
b11 1
b11 ;
b11 E
b11 O
b11 Y
b11 c
b11 m
b11 w
b101 #
b101 &
#75
b10101011 2
b10001001 <
b1100111 F
b1000101 P
b100011 Z
b1 d
b11101111 n
b1100110111101111000000010010001101000101011001111000100110101011 !
b1100110111101111000000010010001101000101011001111000100110101011 (
b11001101 x
b10 '
b10 1
b10 ;
b10 E
b10 O
b10 Y
b10 c
b10 m
b10 w
b110 #
b110 &
#80
b11101111 x
b1 n
b100011 d
b1000101 Z
b1100111 P
b10001001 F
b10101011 <
b1110111100000001001000110100010101100111100010011010101111001101 !
b1110111100000001001000110100010101100111100010011010101111001101 (
b11001101 2
b1 '
b1 1
b1 ;
b1 E
b1 O
b1 Y
b1 c
b1 m
b1 w
b111 #
b111 &
#85
b11101111 2
b11001101 <
b10101011 F
b10001001 P
b1100111 Z
b1000101 d
b100011 n
b100100011010001010110011110001001101010111100110111101111 !
b100100011010001010110011110001001101010111100110111101111 (
b1 x
b0 '
b0 1
b0 ;
b0 E
b0 O
b0 Y
b0 c
b0 m
b0 w
b0 #
b0 &
#90
b100011 x
b1000101 n
b1100111 d
b10001001 Z
b10101011 P
b11001101 F
b11101111 <
b10001101000101011001111000100110101011110011011110111100000001 !
b10001101000101011001111000100110101011110011011110111100000001 (
b1 2
b111 '
b111 1
b111 ;
b111 E
b111 O
b111 Y
b111 c
b111 m
b111 w
b1 #
b1 &
#95
b100011 2
b1 <
b11101111 F
b11001101 P
b10101011 Z
b10001001 d
b1100111 n
b100010101100111100010011010101111001101111011110000000100100011 !
b100010101100111100010011010101111001101111011110000000100100011 (
b1000101 x
b110 '
b110 1
b110 ;
b110 E
b110 O
b110 Y
b110 c
b110 m
b110 w
b10 #
b10 &
#100
b1100111 x
b10001001 n
b10101011 d
b11001101 Z
b11101111 P
b1 F
b100011 <
b110011110001001101010111100110111101111000000010010001101000101 !
b110011110001001101010111100110111101111000000010010001101000101 (
b1000101 2
b101 '
b101 1
b101 ;
b101 E
b101 O
b101 Y
b101 c
b101 m
b101 w
b11 #
b11 &
#105
b1100111 2
b1000101 <
b100011 F
b1 P
b11101111 Z
b11001101 d
b10101011 n
b1000100110101011110011011110111100000001001000110100010101100111 !
b1000100110101011110011011110111100000001001000110100010101100111 (
b10001001 x
b100 '
b100 1
b100 ;
b100 E
b100 O
b100 Y
b100 c
b100 m
b100 w
b100 #
b100 &
#110
b10101011 x
b11001101 n
b11101111 d
b1 Z
b100011 P
b1000101 F
b1100111 <
b1010101111001101111011110000000100100011010001010110011110001001 !
b1010101111001101111011110000000100100011010001010110011110001001 (
b10001001 2
b11 '
b11 1
b11 ;
b11 E
b11 O
b11 Y
b11 c
b11 m
b11 w
b101 #
b101 &
#115
b10101011 2
b10001001 <
b1100111 F
b1000101 P
b100011 Z
b1 d
b11101111 n
b1100110111101111000000010010001101000101011001111000100110101011 !
b1100110111101111000000010010001101000101011001111000100110101011 (
b11001101 x
b10 '
b10 1
b10 ;
b10 E
b10 O
b10 Y
b10 c
b10 m
b10 w
b110 #
b110 &
#120
b11101111 x
b1 n
b100011 d
b1000101 Z
b1100111 P
b10001001 F
b10101011 <
b1110111100000001001000110100010101100111100010011010101111001101 !
b1110111100000001001000110100010101100111100010011010101111001101 (
b11001101 2
b1 '
b1 1
b1 ;
b1 E
b1 O
b1 Y
b1 c
b1 m
b1 w
b111 #
b111 &
#125
b11101111 2
b11001101 <
b10101011 F
b10001001 P
b1100111 Z
b1000101 d
b100011 n
b100100011010001010110011110001001101010111100110111101111 !
b100100011010001010110011110001001101010111100110111101111 (
b1 x
b0 '
b0 1
b0 ;
b0 E
b0 O
b0 Y
b0 c
b0 m
b0 w
b0 #
b0 &
